Tests/__init__.py
cypherpilot-10.0.0.dist-info/LICENSE
cypherpilot-10.0.0.dist-info/METADATA
cypherpilot-10.0.0.dist-info/WHEEL
cypherpilot-10.0.0.dist-info/top_level.txt
cypherpilot-10.0.0.dist-info/RECORD
